MANIFEST.in
README.rst
setup.py
auth_hacks/__init__.py
auth_hacks/models.py
django_auth_hack.egg-info/PKG-INFO
django_auth_hack.egg-info/SOURCES.txt
django_auth_hack.egg-info/dependency_links.txt
django_auth_hack.egg-info/requires.txt
django_auth_hack.egg-info/top_level.txt