Metadata-Version: 1.0
Name: django-auth-hack
Version: 0.1.1
Summary: Hacking Django's contrib auth app to support longer usernames
Home-page: UNKNOWN
Author: Francisco Souza
Author-email: francisco@franciscosouza.net
License: UNKNOWN
Platform: UNKNOWN
